CORDIC/Verilog/counter.v
module cordic_counter (
    input wire clk,
    input wire rst_n,
    input wire start,
    output reg [3:0] iteration_count,
    output wire done
);
parameter MAX_COUNT = 4'd15;
reg counting_active;
wire next_count_0, next_count_1, next_count_2, next_count_3;
assign done = (iteration_count == MAX_COUNT) && counting_active;
assign next_count_0 = ~iteration_count[0];
assign next_count_1 = iteration_count[0] ^ iteration_count[1];
assign next_count_2 = ((~iteration_count[3]) & (~iteration_count[2]) & (iteration_count[1]) & iteration_count[0])
                    | (~iteration_count[0] & iteration_count[2])
                    | (~iteration_count[1] & iteration_count[2])
                    | (~iteration_count[1] & iteration_count[0] & iteration_count[3]);
assign next_count_3 = ((~iteration_count[3]) & (iteration_count[2]) & (iteration_count[1]) & iteration_count[0])
                    | (~iteration_count[0] & iteration_count[3])
                    | (~iteration_count[1] & iteration_count[3])
                    | (~iteration_count[2] & iteration_count[3]);
always @(posedge clk or negedge rst_n) begin
    if (rst_n == 1'b0) begin
        iteration_count <= 4'd0;
        counting_active <= 1'b0;
    end else begin
        if (start) begin
            iteration_count <= 4'd0;
            counting_active <= 1'b1;
        end else if (counting_active) begin
            if (iteration_count < MAX_COUNT) begin
                iteration_count <= {next_count_3, next_count_2, next_count_1, next_count_0};
            end else begin
                counting_active <= 1'b0;
            end
        end
    end
end
endmodule

CORDIC/Verilog/counter_tb.v
// ==============================================================================
// Testbench for cordic_counter module
// Verifies sequential counting from 0 to 15 and the stop condition.
// ==============================================================================

`timescale 1ns / 1ps

module counter_tb;

    // --- Signals for DUT (Device Under Test) ---
    reg clk;
    reg rst_n;
    reg start;
    wire [3:0] iteration_count;
    wire done;

    // --- Clock Generation ---
    parameter CLK_PERIOD = 10; // 10ns period (100 MHz)
    initial begin
        clk = 0;
        forever #(CLK_PERIOD/2) clk = ~clk;
    end

    // --- Instantiate the DUT (Assuming module name is 'cordic_counter' from previous step) ---
    cordic_counter DUT (
        .clk(clk),
        .rst_n(rst_n),
        .start(start),
        .iteration_count(iteration_count),
        .done(done)
    );

    // --- Test Sequence Stimulus ---
    initial begin
        $dumpfile("counter.vcd");
        $dumpvars(0, counter_tb);
        
        // 1. Initial State and Reset
        rst_n = 0;   // Assert Reset
        start = 0;   // Hold Start low
        #5;
        rst_n = 1;   // De-assert Reset (Module is now IDLE)
        $display("Time=%0t: System out of reset. Waiting for start signal.", $time);
        
        // 2. Wait in IDLE state
        #(CLK_PERIOD * 2);

        // 3. Start the Count (Pulse 'start' for one clock cycle)
        $display("Time=%0t: Pulsing START to initiate counting.", $time);
        start = 1;
        #(CLK_PERIOD);
        start = 0;

        // 4. Run the 16 Iterations (0 to 15)
        // CORDIC takes 16 cycles to run, plus 1 cycle for post-processing/done flag
        // We will wait 20 cycles to confirm it stops correctly.
        $display("Time=%0t: Count started. Expected 16 cycles (0-15).", $time);
        
        #(CLK_PERIOD * 20); 
        
        // 5. Verification Checks
        if (iteration_count == 4'd15) begin
            $display("Time=%0t: SUCCESS! Counter stopped at 15.", $time);
        end else begin
            $display("Time=%0t: ERROR! Counter is at %d, expected 15.", $time, iteration_count);
        end

        if (done == 1'b0) begin
            $display("Time=%0t: SUCCESS! Done signal is correctly low after count completion.", $time);
        end else begin
            $display("Time=%0t: ERROR! Done signal is still high.", $time);
        end

        // 6. Test a second run
        $display("\nTime=%0t: Starting second run.", $time);
        start = 1;
        #(CLK_PERIOD);
        start = 0;
        
        #(CLK_PERIOD * 20);
        
        $display("Time=%0t: Simulation finished.", $time);
        $finish;
    end

endmodule

CORDIC/Verilog/counter.vcd
$date
	Tue Oct 28 15:41:39 2025
$end
$version
	Icarus Verilog
$end
$timescale
	1ps
$end
$scope module counter_tb $end
$var wire 4 ! iteration_count [3:0] $end
$var wire 1 " done $end
$var reg 1 # clk $end
$var reg 1 $ rst_n $end
$var reg 1 % start $end
$scope module DUT $end
$var wire 1 # clk $end
$var wire 1 " done $end
$var wire 1 & next_count_0 $end
$var wire 1 ' next_count_1 $end
$var wire 1 ( next_count_2 $end
$var wire 1 ) next_count_3 $end
$var wire 1 $ rst_n $end
$var wire 1 % start $end
$var reg 1 * counting_active $end
$var reg 4 + iteration_count [3:0] $end
$upscope $end
$upscope $end
$enddefinitions $end
#0
$dumpvars
b0 +
0*
0)
0(
0'
1&
0%
0$
0#
0"
b0 !
$end
#5000
1$
1#
#10000
0#
#15000
1#
#20000
0#
#25000
1*
1#
1%
#30000
0#
#35000
0&
1'
b1 !
b1 +
1#
0%
#40000
0#
#45000
1&
b10 !
b10 +
1#
#50000
0#
#55000
1(
0&
0'
b11 !
b11 +
1#
#60000
0#
#65000
1&
b100 !
b100 +
1#
#70000
0#
#75000
0&
1'
b101 !
b101 +
1#
#80000
0#
#85000
1(
1&
b110 !
b110 +
1#
#90000
0#
#95000
0(
1)
0&
0'
b111 !
b111 +
1#
#100000
0#
#105000
1&
b1000 !
b1000 +
1#
#110000
0#
#115000
1(
0&
1'
b1001 !
b1001 +
1#
#120000
0#
#125000
1(
1)
1&
b1110 !
b1110 +
1#
#130000
0#
#135000
0(
0)
0&
0'
1"
b1111 !
b1111 +
1#
#140000
0#
#145000
0"
0*
1#
#150000
0#
#155000
1#
#160000
0#
#165000
1#
#170000
0#
#175000
1#
#180000
0#
#185000
1#
#190000
0#
#195000
1#
#200000
0#
#205000
1#
#210000
0#
#215000
1#
#220000
0#
#225000
1#
#230000
0#
#235000
1&
1*
b0 !
b0 +
1#
1%
#240000
0#
#245000
0&
1'
b1 !
b1 +
1#
0%
#250000
0#
#255000
1&
b10 !
b10 +
1#
#260000
0#
#265000
1(
0&
0'
b11 !
b11 +
1#
#270000
0#
#275000
1&
b100 !
b100 +
1#
#280000
0#
#285000
0&
1'
b101 !
b101 +
1#
#290000
0#
#295000
1(
1&
b110 !
b110 +
1#
#300000
0#
#305000
0(
1)
0&
0'
b111 !
b111 +
1#
#310000
0#
#315000
1&
b1000 !
b1000 +
1#
#320000
0#
#325000
1(
0&
1'
b1001 !
b1001 +
1#
#330000
0#
#335000
1(
1)
1&
b1110 !
b1110 +
1#
#340000
0#
#345000
0(
0)
0&
0'
1"
b1111 !
b1111 +
1#
#350000
0#
#355000
0"
0*
1#
